asyncpause-0.1.1.dist-info/METADATA
asyncpause-0.1.1.dist-info/WHEEL
asyncpause-0.1.1.dist-info/licenses/LICENSE
asyncpause/__init__.py
asyncpause/ap.py
asyncpause/py.typed
asyncpause-0.1.1.dist-info/RECORD
