Metadata-Version: 2.1
Name: asyncpause
Version: 0.1.1
Summary: a Python library to schedule and persist async function calls, ensuring they run exactly when you need them, even after restarts.
Author-Email: Grigory Bakunov <bobuk@rubedo.cloud>
License: Unlicense
Requires-Python: >=3.10
Requires-Dist: aiofiles>=23.0.0
